{
  "1": "مشهد",
  "2": "کرج",
  "3": "شیراز",
  "4": "اصفهان",
  "5": "اهواز",
  "6": "تبریز",
  "7": "کرمانشاه",
  "8": "قم",
  "9": "رشت",
  "10": "آبادان",
  "11": "آباده",
  "12": "آبدانان",
  "13": "آبسرد",
  "14": "آبعلی",
  "15": "آبیک",
  "16": "آذرشهر",
  "17": "آران و بیدگل",
  "18": "آزادشهر",
  "19": "آسارا",
  "20": "آستارا",
  "21": "آستانه اشرفیه",
  "22": "آشخانه",
  "23": "آق قلا",
  "24": "آمل",
  "25": "ابریشم",
  "26": "ابهر",
  "27": "اراک",
  "28": "ارجمند",
  "29": "اردبیل",
  "30": "اردکان",
  "31": "ارومیه",
  "32": "ازنا",
  "33": "اسدآباد",
  "34": "اسفراین",
  "35": "اسلام‌‌آباد غرب",
  "36": "اسلام‌شهر",
  "37": "اشتهارد",
  "38": "اشنویه",
  "39": "اصفهان",
  "40": "اقلید",
  "41": "الوند",
  "42": "الیگودرز",
  "43": "املش",
  "44": "امیرکلا",
  "45": "اندیمشک",
  "46": "اهر",
  "47": "اهواز",
  "48": "ایذه",
  "49": "ایرانشهر",
  "50": "ایزدشهر",
  "51": "ایلام",
  "52": "ایوان",
  "53": "بابل",
  "54": "بابلسر",
  "55": "باقرشهر",
  "56": "بانه",
  "57": "بجنورد",
  "58": "برازجان",
  "59": "بردسکن",
  "60": "بروجرد",
  "61": "بروجن",
  "62": "بم",
  "63": "بناب",
  "64": "بندر امام خمینی",
  "65": "بندر انزلی",
  "66": "بندر ترکمن",
  "67": "بندرعباس",
  "68": "بندر کنگان",
  "69": "بندر گناوه",
  "70": "بندر ماهشهر",
  "71": "بوشهر",
  "72": "بوکان",
  "73": "بهبهان",
  "74": "بهشهر",
  "75": "بیجار",
  "76": "بیرجند",
  "77": "پارس‌آباد",
  "78": "پل سفید",
  "79": "پیرانشهر",
  "80": "پیشوا",
  "81": "تاکستان",
  "82": "تالش",
  "83": "تایباد",
  "84": "تبریز",
  "85": "تربت جام",
  "86": "تنکابن",
  "87": "تنکمان",
  "88": "تویسرکان",
  "89": "تهران",
  "90": "جوادآباد",
  "91": "جوانرود",
  "92": "جویبار",
  "93": "جهرم",
  "94": "جیرفت",
  "95": "چابکسر",
  "96": "چابهار",
  "97": "چاف و چمخاله",
  "98": "چالوس",
  "99": "چمستان",
  "100": "چناران",
  "101": "چهارباغ",
  "102": "چهاردانگه",
  "103": "حمیدیا",
  "104": "خرم‌آباد",
  "105": "خرمدره",
  "106": "خرمشهر",
  "107": "خشکبیجار",
  "108": "خلخال",
  "109": "خمین",
  "110": "خواف",
  "111": "خوانسار",
  "112": "خوی",
  "113": "داراب",
  "114": "داران",
  "115": "دامغان",
  "116": "دزفول",
  "117": "دماوند",
  "118": "دورود",
  "119": "دوگنبدان",
  "120": "دهدشت",
  "121": "دهلران",
  "122": "رامسر",
  "123": "رامهرمز",
  "124": "رشت",
  "125": "رضوانشهر",
  "126": "رفسنجان",
  "127": "رودسر",
  "128": "رویان",
  "129": "زابل",
  "130": "زاهدان",
  "131": "زرند",
  "132": "زنجان",
  "133": "زیباکنار",
  "134": "ساری",
  "135": "ساوه",
  "136": "سبزوار",
  "137": "سراب",
  "138": "سراوان-سیستان و بلوچستان",
  "139": "سرپل ذهاب",
  "140": "سرخرود",
  "141": "سردشت",
  "142": "سقز",
  "143": "سلماس",
  "144": "سلمان‌شهر",
  "145": "سمنان",
  "146": "سمیرم",
  "147": "سنقر",
  "148": "سنندج",
  "149": "سوسنگرد",
  "150": "سهند",
  "151": "سیاهکل",
  "152": "سیرجان",
  "153": "شاهدشهر",
  "154": "شاهرود",
  "155": "شاهین دژ",
  "156": "شمشک",
  "157": "شوش",
  "158": "شوشتر",
  "159": "شهرکرد",
  "160": "شیراز",
  "161": "شیروان",
  "162": "صباشهر",
  "163": "صدرا-فارس",
  "164": "صفادشت",
  "165": "صومعه‌سرا",
  "166": "طالقان",
  "167": "طبس",
  "168": "عباس‌آباد",
  "169": "علی‌آباد کتول",
  "170": "فرخ‌شهر",
  "171": "فردوس",
  "172": "فردوسیه",
  "173": "فریدون‌کنار",
  "174": "فلاورجان",
  "175": "فومن",
  "176": "فیروزآباد",
  "177": "قائم‌شهر",
  "178": "قاسم‌آباد (خواف)",
  "179": "قاين",
  "180": "قروه",
  "181": "قزوین",
  "182": "قشم",
  "183": "قم",
  "184": "قیدار",
  "185": "کاشان",
  "186": "کرج",
  "187": "کردکوی",
  "188": "کرمان",
  "189": "کرمانشاه",
  "190": "کلاچای",
  "191": "کلارآباد",
  "192": "کلاردشت",
  "193": "کلاله",
  "194": "کنگاور",
  "195": "کوهدشت",
  "196": "کوهسار",
  "197": "کهریزک",
  "198": "کیاشهر",
  "199": "کیش",
  "200": "کیلان",
  "201": "گرگان",
  "202": "گرمدره",
  "203": "گرمسار",
  "204": "گلپایگان",
  "205": "گلستان",
  "206": "گمیشان",
  "207": "گناباد",
  "208": "گنبد کاووس",
  "209": "لار",
  "210": "لامرد",
  "211": "لاهیجان",
  "212": "لردگان",
  "213": "لشت نشا",
  "214": "لنگرود",
  "215": "ماسال",
  "216": "ماکو",
  "217": "محلات",
  "218": "محمدیه-قزوین",
  "219": "محمودآباد",
  "220": "مراغه",
  "221": "مرند",
  "222": "مریوان",
  "223": "مسجد سلیمان",
  "224": "مشکین‌شهر",
  "225": "مشهد",
  "226": "ملایر",
  "227": "مهاباد",
  "228": "میاندوآب",
  "229": "میانه",
  "230": "میبد",
  "231": "میناب",
  "232": "مینودشت",
  "233": "نجف‌آباد",
  "234": "نسیم‌شهر",
  "235": "نظرآباد",
  "236": "نقده",
  "237": "نکا",
  "238": "نور",
  "239": "نورآباد",
  "240": "نوشهر",
  "241": "نهاوند",
  "242": "نی‌ریز",
  "243": "نیشابور",
  "244": "وحیدیه",
  "245": "همدان",
  "246": "یاسوج",
  "247": "یزد"
}